oasm/dev/__init__.py
oasm/dev/flex.py
oasm/dev/std.py
oasm_dev-0.1.17.dist-info/METADATA
oasm_dev-0.1.17.dist-info/WHEEL
oasm_dev-0.1.17.dist-info/top_level.txt
oasm_dev-0.1.17.dist-info/RECORD
