Metadata-Version: 2.4
Name: oasm.dev
Version: 0.1.17
Summary: Open ASseMbly tools - DEVices
Author-email: nzturn <nzturn@gmail.com>
Keywords: asm,dsl
Classifier: Development Status :: 3 - Alpha
Classifier: Intended Audience :: Developers
Classifier: Programming Language :: Python :: 3
Requires-Python: >=3.8
Requires-Dist: oasm.rtmq2
Requires-Dist: pyserial
Requires-Dist: PyD3XX
